LICENSE
MANIFEST.in
README.md
requirements.txt
setup.cfg
setup.py
notebook_image_tabs/__init__.py
notebook_image_tabs/__meta__.py
notebook_image_tabs/params.py
notebook_image_tabs/template.py
notebook_image_tabs/util.py
notebook_image_tabs/viewer.py
notebook_image_tabs.egg-info/PKG-INFO
notebook_image_tabs.egg-info/SOURCES.txt
notebook_image_tabs.egg-info/dependency_links.txt
notebook_image_tabs.egg-info/not-zip-safe
notebook_image_tabs.egg-info/requires.txt
notebook_image_tabs.egg-info/top_level.txt
notebook_image_tabs/templates/iframe.tpl.html
notebook_image_tabs/templates/main.tpl.html
notebook_image_tabs/templates/script.tpl.js