Metadata-Version: 1.1
Name: notebook-image-tabs
Version: 0.2.3
Summary: display several images under tabs
Home-page: https://github.com/oscar6echo/notebook-image-tabs
Author: oscar6echo
Author-email: olivier.borderies@gmail.com
License: MIT
Download-URL: https://github.com/oscar6echo/notebook-image-tabs/tarball/0.2.3
Keywords: javascript,tab,image,display
Platform: UNKNOWN
Classifier: Development Status :: 4 - Beta
Classifier: License :: OSI Approved :: MIT License
Classifier: Programming Language :: Python :: 3.5
Classifier: Programming Language :: Python :: 3.6
